<?xml version="1.0" encoding="UTF-8"?>
<Root>
  <PM_HEADER>
    <DONE_IRR>true</DONE_IRR>
  </PM_HEADER>
  <PARTIAL_MATRIX>
    <PARTIAL_DYN>
   3.104652770380372E+00   4.071175365559349E-18
  -3.115563362854346E-15  -6.629558328877345E-09
  -1.823796849981481E-01  -1.349069012598378E-18
   1.677245715774917E-01  -8.725675484450721E-19
   3.774758283725532E-15  -3.038771471864158E-16
   1.153591111524577E-16   5.272968192138310E-16
  -3.087807787238717E-15   6.629558316026306E-09
   6.419692620766146E+00   4.071174228185869E-18
  -3.004541060391830E-15   2.391974897321916E-16
   8.921682836948719E-15  -5.305875387111139E-16
  -1.969612097426552E-01  -1.263596840346136E-18
   1.503335068026650E-01  -9.923023721610074E-19
  -1.823796849981479E-01  -1.652934386152280E-18
  -2.782496455466799E-15  -3.433035193517211E-16
   4.341110499566946E+00  -4.234445779471207E-18
   1.953815355358353E-01  -1.711990383049884E-18
  -5.814793091474257E-15  -2.628267719064256E-09
  -2.761679773755077E-15  -2.414965224853100E-10
   1.677245715774918E-01  -6.375070950121912E-19
   8.706143445058601E-15   7.968431030624461E-16
   1.953815355358354E-01  -1.425780591909022E-18
   4.271594675976774E+00   2.916610728526046E-18
  -2.163633855412073E-15   2.414954012933509E-10
  -1.737325561190772E-15  -2.628266343007142E-09
   3.885780586188048E-15   3.972919491349454E-16
  -1.969612097426551E-01  -1.587643790471561E-18
  -5.648259637780484E-15   2.628267734312216E-09
  -2.157128642377160E-15  -2.414952778410480E-10
   2.647404268336147E+00  -3.888679665465866E-18
   1.984439885209015E-01  -2.337286313842700E-18
   8.847089727481716E-17  -7.405691074641057E-16
   1.503335068026651E-01  -7.861165305777595E-19
  -2.728720027711518E-15   2.414963849210608E-10
  -1.842926852790860E-15   2.628266333000317E-09
   1.984439885209018E-01  -2.051080167466411E-18
   2.650261036167065E+00   2.570844456596950E-18
    </PARTIAL_DYN>
  </PARTIAL_MATRIX>
</Root>
