<?xml version="1.0" encoding="UTF-8"?>
<Root>
  <PM_HEADER>
    <DONE_IRR>true</DONE_IRR>
  </PM_HEADER>
  <PARTIAL_MATRIX>
    <PARTIAL_DYN>
   0.000000000000000E+00   0.000000000000000E+00
   0.000000000000000E+00   0.000000000000000E+00
   0.000000000000000E+00   0.000000000000000E+00
   0.000000000000000E+00   0.000000000000000E+00
   0.000000000000000E+00   0.000000000000000E+00
  -8.796952504493626E-02   5.851824316828645E-01
   0.000000000000000E+00   0.000000000000000E+00
   0.000000000000000E+00   0.000000000000000E+00
   0.000000000000000E+00   0.000000000000000E+00
   0.000000000000000E+00   0.000000000000000E+00
   0.000000000000000E+00   0.000000000000000E+00
  -2.436007097227929E-02   1.224546022426313E-02
   0.000000000000000E+00   0.000000000000000E+00
   0.000000000000000E+00   0.000000000000000E+00
   0.000000000000000E+00   0.000000000000000E+00
   0.000000000000000E+00   0.000000000000000E+00
   0.000000000000000E+00   0.000000000000000E+00
   1.790208911623429E-02   4.520917610759268E-02
   0.000000000000000E+00   0.000000000000000E+00
   0.000000000000000E+00   0.000000000000000E+00
   0.000000000000000E+00   0.000000000000000E+00
   0.000000000000000E+00   0.000000000000000E+00
   0.000000000000000E+00   0.000000000000000E+00
   3.665455494355550E-01  -6.331903372139533E-01
   0.000000000000000E+00   0.000000000000000E+00
   0.000000000000000E+00   0.000000000000000E+00
   0.000000000000000E+00   0.000000000000000E+00
   0.000000000000000E+00   0.000000000000000E+00
   0.000000000000000E+00   0.000000000000000E+00
   2.051842089852427E-02   2.245022666038563E-03
   0.000000000000000E+00   0.000000000000000E+00
   0.000000000000000E+00   0.000000000000000E+00
   0.000000000000000E+00   0.000000000000000E+00
   0.000000000000000E+00   0.000000000000000E+00
   0.000000000000000E+00   0.000000000000000E+00
  -3.393794303903372E+00   2.158392184167346E-07
    </PARTIAL_DYN>
  </PARTIAL_MATRIX>
</Root>
